dbt/dbt_project.yml
dbt/profiles.yml
dbt/models/sources.yml
lung_sarg/__init__.py
lung_sarg/resources.py
lung_sarg/sensors.py
lung_sarg-1.0.0.dist-info/LICENSE
lung_sarg-1.0.0.dist-info/METADATA
lung_sarg-1.0.0.dist-info/WHEEL
lung_sarg-1.0.0.dist-info/top_level.txt
lung_sarg-1.0.0.dist-info/RECORD
