Metadata-Version: 2.1
Name: lung-sarg
Version: 1.0.0
Author: Matt McCormick
License: MIT
Project-URL: Homepage, https://radiogenomics.github.io/lung-sarg/
Project-URL: Changelog, https://github.com/open-radiogenomics/lung-sarg/commits/main/
Project-URL: Issues, https://github.com/open-radiogenomics/lung-sarg/issues
Project-URL: CI, https://github.com/open-radiogenomics/lung-sarg/actions
Requires-Python: <=3.13,>=3.11
License-File: LICENSE
Requires-Dist: dagster-dbt ==0.23.16
Requires-Dist: dagster-duckdb-polars ==0.23.16
Requires-Dist: dagster-duckdb
Requires-Dist: dagster ==1.7.16
Requires-Dist: datasets
Requires-Dist: dbt-core
Requires-Dist: dbt-duckdb
Requires-Dist: duckdb ==1.0.0
Requires-Dist: huggingface-hub
Requires-Dist: httpx[http2]
Requires-Dist: pyarrow
Requires-Dist: python-slugify
Requires-Dist: tenacity
Requires-Dist: itk <6,>=5.4.0
Requires-Dist: ngff-zarr[dask-image,itk] <0.9,>=0.8.5
Requires-Dist: pip <25,>=24.2
Requires-Dist: build <2,>=1.2.1
Provides-Extra: dev
Requires-Dist: dagster-webserver ==1.7.16 ; extra == 'dev'
Requires-Dist: ruff ; extra == 'dev'
